pytest_pahrametahrize.py
pytest_pahrametahrize-1.0.0.dist-info/entry_points.txt
pytest_pahrametahrize-1.0.0.dist-info/LICENSE
pytest_pahrametahrize-1.0.0.dist-info/WHEEL
pytest_pahrametahrize-1.0.0.dist-info/METADATA
pytest_pahrametahrize-1.0.0.dist-info/RECORD
